yapr/__init__.py
yapr/db/conn.py
yapr/db/models.py
yapr/llm.py
yapr/models.py
yapr/prompt.py
yapr/util.py
yapr-0.1.1.dist-info/LICENSE
yapr-0.1.1.dist-info/METADATA
yapr-0.1.1.dist-info/WHEEL
yapr-0.1.1.dist-info/RECORD
